blue/__init__.py
blue/agent.py
blue/bluelock.py
blue/connection.py
blue/constant.py
blue/core.py
blue/metadata.py
blue/model.py
blue/platform.py
blue/properties.py
blue/pubsub.py
blue/registry.py
blue/scheduler.py
blue/service.py
blue/session.py
blue/stream.py
blue/tracker.py
blue/agents/__init__.py
blue/agents/blocking_agent.py
blue/agents/coordinator.py
blue/agents/documenter.py
blue/agents/nl2llm.py
blue/agents/nl2q.py
blue/agents/observer.py
blue/agents/openai.py
blue/agents/plan.py
blue/agents/presenter.py
blue/agents/query_executor.py
blue/agents/recorder.py
blue/agents/registry.py
blue/agents/requestor.py
blue/agents/summarizer.py
blue/agents/user.py
blue/agents/visualizer.py
blue/data/__init__.py
blue/data/pipeline.py
blue/data/planner.py
blue/data/prompt_templates.py
blue/data/registry.py
blue/data/schema.py
blue/data/source.py
blue/data/sources/__init__.py
blue/data/sources/mongodb_source.py
blue/data/sources/mysql_source.py
blue/data/sources/neo4j_source.py
blue/data/sources/openai_source.py
blue/data/sources/postgres_source.py
blue/data/sources/sqlite_source.py
blue/operators/__init__.py
blue/operators/client.py
blue/operators/create_database_operator.py
blue/operators/create_table_operator.py
blue/operators/data_discover_operator.py
blue/operators/delete_operator.py
blue/operators/insert_operator.py
blue/operators/insert_table_operator.py
blue/operators/intersect_operator.py
blue/operators/join_operator.py
blue/operators/multipart_query_operator.py
blue/operators/nl2llm_operator.py
blue/operators/nl2query_router_operator.py
blue/operators/nl2sql_operator.py
blue/operators/operator.py
blue/operators/operator_discover.py
blue/operators/plan_discover.py
blue/operators/project_operator.py
blue/operators/query_breakdown_operator.py
blue/operators/registry.py
blue/operators/select_operator.py
blue/operators/semantic_extract_operator.py
blue/operators/semantic_filter_operator.py
blue/operators/semantic_project_operator.py
blue_platform-1.0.dist-info/licenses/LICENSE
blue_platform-1.0.dist-info/METADATA
blue_platform-1.0.dist-info/WHEEL
blue_platform-1.0.dist-info/top_level.txt
blue_platform-1.0.dist-info/RECORD
