Metadata-Version: 2.4
Name: blue-platform
Version: 1.0
Summary: Streams-based agent orchestration platform for building and deploying applications with agentic workflows for the enterprise
Author-email: Megagon Labs <blue@megagon.ai>
License-Expression: BSD-3-Clause
Project-URL: Homepage, https://github.com/megagonlabs/blue
Project-URL: Issues, https://github.com/megagonlabs/blue/issues
Project-URL: Discussions, https://github.com/megagonlabs/blue/discussions
Classifier: Development Status :: 4 - Beta
Classifier: Programming Language :: Python :: 3.9
Classifier: Operating System :: OS Independent
Requires-Python: >=3.9
License-File: LICENSE
Dynamic: license-file
